hylightpy/__init__.py
hylightpy/hylightpy.py
hylightpy/data/Einstein_As_150.txt
hylightpy/data/h_coll_str.dat
hylightpy/data/h_iso_recomb_HI_150.dat
hylightpy-0.0.23.dist-info/METADATA
hylightpy-0.0.23.dist-info/WHEEL
hylightpy-0.0.23.dist-info/licenses/LICENSE
hylightpy-0.0.23.dist-info/RECORD
