Metadata-Version: 2.4
Name: hylightpy
Version: 0.0.23
Summary: Atomic model for hydrogen recombination lines.
Project-URL: Homepage, https://github.com/YuankangLiu/HyLight
Project-URL: Issues, https://github.com/YuankangLiu/HyLight/issues
Author-email: Yuankang Liu <yuankang.liu@gmail.com>, Tom Theuns <tom.theuns@gmail.com>
License-Expression: MIT
License-File: LICENSE
Classifier: Operating System :: OS Independent
Classifier: Programming Language :: Python :: 3
Requires-Python: >=3.9
Requires-Dist: numpy>=1.19.0
Requires-Dist: pandas>=2.2.0
Requires-Dist: scipy>=1.14.0
Requires-Dist: unyt>=3.0.0
